Workbook

Sheet Annual Summary
A1: Month | B1: Income | C1: Expenses | D1: Net Savings | E1: Savings Rate
A2: January | B2: ='January'!B2 | C2: ='January'!B3 | D2: =B2-C2 | E2: =IF(B2>0,(B2-C2)/B2,0)
A3: February | B3: ='February'!B2 | C3: ='February'!B3 | D3: =B3-C3 | E3: =IF(B3>0,(B3-C3)/B3,0)
A4: March | B4: ='March'!B2 | C4: ='March'!B3 | D4: =B4-C4 | E4: =IF(B4>0,(B4-C4)/B4,0)
A5: April | B5: ='April'!B2 | C5: ='April'!B3 | D5: =B5-C5 | E5: =IF(B5>0,(B5-C5)/B5,0)
A6: May | B6: ='May'!B2 | C6: ='May'!B3 | D6: =B6-C6 | E6: =IF(B6>0,(B6-C6)/B6,0)
A7: June | B7: ='June'!B2 | C7: ='June'!B3 | D7: =B7-C7 | E7: =IF(B7>0,(B7-C7)/B7,0)
A8: July | B8: ='July'!B2 | C8: ='July'!B3 | D8: =B8-C8 | E8: =IF(B8>0,(B8-C8)/B8,0)
A9: August | B9: ='August'!B2 | C9: ='August'!B3 | D9: =B9-C9 | E9: =IF(B9>0,(B9-C9)/B9,0)
A10: September | B10: ='September'!B2 | C10: ='September'!B3 | D10: =B10-C10 | E10: =IF(B10>0,(B10-C10)/B10,0)
A11: October | B11: ='October'!B2 | C11: ='October'!B3 | D11: =B11-C11 | E11: =IF(B11>0,(B11-C11)/B11,0)
A12: November | B12: ='November'!B2 | C12: ='November'!B3 | D12: =B12-C12 | E12: =IF(B12>0,(B12-C12)/B12,0)
A13: December | B13: ='December'!B2 | C13: ='December'!B3 | D13: =B13-C13 | E13: =IF(B13>0,(B13-C13)/B13,0)
A14: TOTAL | B14: =SUM(B2:B13) | C14: =SUM(C2:C13) | D14: =B14-C14 | E14: =IF(B14>0,(B14-C14)/B14,0)

Sheet January
A1: Total Income: | B1: =SUMIF(E6:E100,"Income",D6:D100) | G1: Category Breakdown
A2: Total Expenses: | B2: =SUMIF(E6:E100,"Expense",D6:D100) | G2: Food & Dining | H2: =SUMIFS(D6:D100,C6:C100,"Food & Dining",E6:E100,"Expense")
A3: Net Savings: | B3: =B1-B2 | G3: Transport | H3: =SUMIFS(D6:D100,C6:C100,"Transport",E6:E100,"Expense")
G4: Housing | H4: =SUMIFS(D6:D100,C6:C100,"Housing",E6:E100,"Expense")
A5: Date | B5: Description | C5: Category | D5: Amount | E5: Type | G5: Utilities | H5: =SUMIFS(D6:D100,C6:C100,"Utilities",E6:E100,"Expense")
A6: 45658 | B6: Monthly Salary | C6: Salary | D6: 5000 | E6: Income | G6: Entertainment | H6: =SUMIFS(D6:D100,C6:C100,"Entertainment",E6:E100,"Expense")
A7: 45660 | B7: Rent Payment | C7: Housing | D7: 1500 | E7: Expense | G7: Shopping | H7: =SUMIFS(D6:D100,C6:C100,"Shopping",E6:E100,"Expense")
A8: 45662 | B8: Grocery Shopping | C8: Food & Dining | D8: 120 | E8: Expense | G8: Healthcare | H8: =SUMIFS(D6:D100,C6:C100,"Healthcare",E6:E100,"Expense")
A9: 45665 | B9: Electric Bill | C9: Utilities | D9: 85 | E9: Expense | G9: Education | H9: =SUMIFS(D6:D100,C6:C100,"Education",E6:E100,"Expense")
A10: 45667 | B10: Netflix | C10: Entertainment | D10: 15 | E10: Expense | G10: Savings | H10: =SUMIFS(D6:D100,C6:C100,"Savings",E6:E100,"Expense")
A11: 45672 | B11: Freelance Project | C11: Freelance | D11: 800 | E11: Income | G11: Other | H11: =SUMIFS(D6:D100,C6:C100,"Other",E6:E100,"Expense")
A12: 45675 | B12: Gas | C12: Transport | D12: 45 | E12: Expense
A13: 45679 | B13: New Shoes | C13: Shopping | D13: 90 | E13: Expense

Sheet February
A1: Total Income: | B1: =SUMIF(E6:E100,"Income",D6:D100) | G1: Category Breakdown
A2: Total Expenses: | B2: =SUMIF(E6:E100,"Expense",D6:D100) | G2: Food & Dining | H2: =SUMIFS(D6:D100,C6:C100,"Food & Dining",E6:E100,"Expense")
A3: Net Savings: | B3: =B1-B2 | G3: Transport | H3: =SUMIFS(D6:D100,C6:C100,"Transport",E6:E100,"Expense")
G4: Housing | H4: =SUMIFS(D6:D100,C6:C100,"Housing",E6:E100,"Expense")
A5: Date | B5: Description | C5: Category | D5: Amount | E5: Type | G5: Utilities | H5: =SUMIFS(D6:D100,C6:C100,"Utilities",E6:E100,"Expense")
G6: Entertainment | H6: =SUMIFS(D6:D100,C6:C100,"Entertainment",E6:E100,"Expense")
G7: Shopping | H7: =SUMIFS(D6:D100,C6:C100,"Shopping",E6:E100,"Expense")
G8: Healthcare | H8: =SUMIFS(D6:D100,C6:C100,"Healthcare",E6:E100,"Expense")
G9: Education | H9: =SUMIFS(D6:D100,C6:C100,"Education",E6:E100,"Expense")
G10: Savings | H10: =SUMIFS(D6:D100,C6:C100,"Savings",E6:E100,"Expense")
G11: Other | H11: =SUMIFS(D6:D100,C6:C100,"Other",E6:E100,"Expense")

Sheet March
A1: Total Income: | B1: =SUMIF(E6:E100,"Income",D6:D100) | G1: Category Breakdown
A2: Total Expenses: | B2: =SUMIF(E6:E100,"Expense",D6:D100) | G2: Food & Dining | H2: =SUMIFS(D6:D100,C6:C100,"Food & Dining",E6:E100,"Expense")
A3: Net Savings: | B3: =B1-B2 | G3: Transport | H3: =SUMIFS(D6:D100,C6:C100,"Transport",E6:E100,"Expense")
G4: Housing | H4: =SUMIFS(D6:D100,C6:C100,"Housing",E6:E100,"Expense")
A5: Date | B5: Description | C5: Category | D5: Amount | E5: Type | G5: Utilities | H5: =SUMIFS(D6:D100,C6:C100,"Utilities",E6:E100,"Expense")
G6: Entertainment | H6: =SUMIFS(D6:D100,C6:C100,"Entertainment",E6:E100,"Expense")
G7: Shopping | H7: =SUMIFS(D6:D100,C6:C100,"Shopping",E6:E100,"Expense")
G8: Healthcare | H8: =SUMIFS(D6:D100,C6:C100,"Healthcare",E6:E100,"Expense")
G9: Education | H9: =SUMIFS(D6:D100,C6:C100,"Education",E6:E100,"Expense")
G10: Savings | H10: =SUMIFS(D6:D100,C6:C100,"Savings",E6:E100,"Expense")
G11: Other | H11: =SUMIFS(D6:D100,C6:C100,"Other",E6:E100,"Expense")

Sheet April
A1: Total Income: | B1: =SUMIF(E6:E100,"Income",D6:D100) | G1: Category Breakdown
A2: Total Expenses: | B2: =SUMIF(E6:E100,"Expense",D6:D100) | G2: Food & Dining | H2: =SUMIFS(D6:D100,C6:C100,"Food & Dining",E6:E100,"Expense")
A3: Net Savings: | B3: =B1-B2 | G3: Transport | H3: =SUMIFS(D6:D100,C6:C100,"Transport",E6:E100,"Expense")
G4: Housing | H4: =SUMIFS(D6:D100,C6:C100,"Housing",E6:E100,"Expense")
A5: Date | B5: Description | C5: Category | D5: Amount | E5: Type | G5: Utilities | H5: =SUMIFS(D6:D100,C6:C100,"Utilities",E6:E100,"Expense")
G6: Entertainment | H6: =SUMIFS(D6:D100,C6:C100,"Entertainment",E6:E100,"Expense")
G7: Shopping | H7: =SUMIFS(D6:D100,C6:C100,"Shopping",E6:E100,"Expense")
G8: Healthcare | H8: =SUMIFS(D6:D100,C6:C100,"Healthcare",E6:E100,"Expense")
G9: Education | H9: =SUMIFS(D6:D100,C6:C100,"Education",E6:E100,"Expense")
G10: Savings | H10: =SUMIFS(D6:D100,C6:C100,"Savings",E6:E100,"Expense")
G11: Other | H11: =SUMIFS(D6:D100,C6:C100,"Other",E6:E100,"Expense")

Sheet May
A1: Total Income: | B1: =SUMIF(E6:E100,"Income",D6:D100) | G1: Category Breakdown
A2: Total Expenses: | B2: =SUMIF(E6:E100,"Expense",D6:D100) | G2: Food & Dining | H2: =SUMIFS(D6:D100,C6:C100,"Food & Dining",E6:E100,"Expense")
A3: Net Savings: | B3: =B1-B2 | G3: Transport | H3: =SUMIFS(D6:D100,C6:C100,"Transport",E6:E100,"Expense")
G4: Housing | H4: =SUMIFS(D6:D100,C6:C100,"Housing",E6:E100,"Expense")
A5: Date | B5: Description | C5: Category | D5: Amount | E5: Type | G5: Utilities | H5: =SUMIFS(D6:D100,C6:C100,"Utilities",E6:E100,"Expense")
G6: Entertainment | H6: =SUMIFS(D6:D100,C6:C100,"Entertainment",E6:E100,"Expense")
G7: Shopping | H7: =SUMIFS(D6:D100,C6:C100,"Shopping",E6:E100,"Expense")
G8: Healthcare | H8: =SUMIFS(D6:D100,C6:C100,"Healthcare",E6:E100,"Expense")
G9: Education | H9: =SUMIFS(D6:D100,C6:C100,"Education",E6:E100,"Expense")
G10: Savings | H10: =SUMIFS(D6:D100,C6:C100,"Savings",E6:E100,"Expense")
G11: Other | H11: =SUMIFS(D6:D100,C6:C100,"Other",E6:E100,"Expense")

Sheet June
A1: Total Income: | B1: =SUMIF(E6:E100,"Income",D6:D100) | G1: Category Breakdown
A2: Total Expenses: | B2: =SUMIF(E6:E100,"Expense",D6:D100) | G2: Food & Dining | H2: =SUMIFS(D6:D100,C6:C100,"Food & Dining",E6:E100,"Expense")
A3: Net Savings: | B3: =B1-B2 | G3: Transport | H3: =SUMIFS(D6:D100,C6:C100,"Transport",E6:E100,"Expense")
G4: Housing | H4: =SUMIFS(D6:D100,C6:C100,"Housing",E6:E100,"Expense")
A5: Date | B5: Description | C5: Category | D5: Amount | E5: Type | G5: Utilities | H5: =SUMIFS(D6:D100,C6:C100,"Utilities",E6:E100,"Expense")
G6: Entertainment | H6: =SUMIFS(D6:D100,C6:C100,"Entertainment",E6:E100,"Expense")
G7: Shopping | H7: =SUMIFS(D6:D100,C6:C100,"Shopping",E6:E100,"Expense")
G8: Healthcare | H8: =SUMIFS(D6:D100,C6:C100,"Healthcare",E6:E100,"Expense")
G9: Education | H9: =SUMIFS(D6:D100,C6:C100,"Education",E6:E100,"Expense")
G10: Savings | H10: =SUMIFS(D6:D100,C6:C100,"Savings",E6:E100,"Expense")
G11: Other | H11: =SUMIFS(D6:D100,C6:C100,"Other",E6:E100,"Expense")

Sheet July
A1: Total Income: | B1: =SUMIF(E6:E100,"Income",D6:D100) | G1: Category Breakdown
A2: Total Expenses: | B2: =SUMIF(E6:E100,"Expense",D6:D100) | G2: Food & Dining | H2: =SUMIFS(D6:D100,C6:C100,"Food & Dining",E6:E100,"Expense")
A3: Net Savings: | B3: =B1-B2 | G3: Transport | H3: =SUMIFS(D6:D100,C6:C100,"Transport",E6:E100,"Expense")
G4: Housing | H4: =SUMIFS(D6:D100,C6:C100,"Housing",E6:E100,"Expense")
A5: Date | B5: Description | C5: Category | D5: Amount | E5: Type | G5: Utilities | H5: =SUMIFS(D6:D100,C6:C100,"Utilities",E6:E100,"Expense")
G6: Entertainment | H6: =SUMIFS(D6:D100,C6:C100,"Entertainment",E6:E100,"Expense")
G7: Shopping | H7: =SUMIFS(D6:D100,C6:C100,"Shopping",E6:E100,"Expense")
G8: Healthcare | H8: =SUMIFS(D6:D100,C6:C100,"Healthcare",E6:E100,"Expense")
G9: Education | H9: =SUMIFS(D6:D100,C6:C100,"Education",E6:E100,"Expense")
G10: Savings | H10: =SUMIFS(D6:D100,C6:C100,"Savings",E6:E100,"Expense")
G11: Other | H11: =SUMIFS(D6:D100,C6:C100,"Other",E6:E100,"Expense")

Sheet August
A1: Total Income: | B1: =SUMIF(E6:E100,"Income",D6:D100) | G1: Category Breakdown
A2: Total Expenses: | B2: =SUMIF(E6:E100,"Expense",D6:D100) | G2: Food & Dining | H2: =SUMIFS(D6:D100,C6:C100,"Food & Dining",E6:E100,"Expense")
A3: Net Savings: | B3: =B1-B2 | G3: Transport | H3: =SUMIFS(D6:D100,C6:C100,"Transport",E6:E100,"Expense")
G4: Housing | H4: =SUMIFS(D6:D100,C6:C100,"Housing",E6:E100,"Expense")
A5: Date | B5: Description | C5: Category | D5: Amount | E5: Type | G5: Utilities | H5: =SUMIFS(D6:D100,C6:C100,"Utilities",E6:E100,"Expense")
G6: Entertainment | H6: =SUMIFS(D6:D100,C6:C100,"Entertainment",E6:E100,"Expense")
G7: Shopping | H7: =SUMIFS(D6:D100,C6:C100,"Shopping",E6:E100,"Expense")
G8: Healthcare | H8: =SUMIFS(D6:D100,C6:C100,"Healthcare",E6:E100,"Expense")
G9: Education | H9: =SUMIFS(D6:D100,C6:C100,"Education",E6:E100,"Expense")
G10: Savings | H10: =SUMIFS(D6:D100,C6:C100,"Savings",E6:E100,"Expense")
G11: Other | H11: =SUMIFS(D6:D100,C6:C100,"Other",E6:E100,"Expense")

Sheet September
A1: Total Income: | B1: =SUMIF(E6:E100,"Income",D6:D100) | G1: Category Breakdown
A2: Total Expenses: | B2: =SUMIF(E6:E100,"Expense",D6:D100) | G2: Food & Dining | H2: =SUMIFS(D6:D100,C6:C100,"Food & Dining",E6:E100,"Expense")
A3: Net Savings: | B3: =B1-B2 | G3: Transport | H3: =SUMIFS(D6:D100,C6:C100,"Transport",E6:E100,"Expense")
G4: Housing | H4: =SUMIFS(D6:D100,C6:C100,"Housing",E6:E100,"Expense")
A5: Date | B5: Description | C5: Category | D5: Amount | E5: Type | G5: Utilities | H5: =SUMIFS(D6:D100,C6:C100,"Utilities",E6:E100,"Expense")
G6: Entertainment | H6: =SUMIFS(D6:D100,C6:C100,"Entertainment",E6:E100,"Expense")
G7: Shopping | H7: =SUMIFS(D6:D100,C6:C100,"Shopping",E6:E100,"Expense")
G8: Healthcare | H8: =SUMIFS(D6:D100,C6:C100,"Healthcare",E6:E100,"Expense")
G9: Education | H9: =SUMIFS(D6:D100,C6:C100,"Education",E6:E100,"Expense")
G10: Savings | H10: =SUMIFS(D6:D100,C6:C100,"Savings",E6:E100,"Expense")
G11: Other | H11: =SUMIFS(D6:D100,C6:C100,"Other",E6:E100,"Expense")

Sheet October
A1: Total Income: | B1: =SUMIF(E6:E100,"Income",D6:D100) | G1: Category Breakdown
A2: Total Expenses: | B2: =SUMIF(E6:E100,"Expense",D6:D100) | G2: Food & Dining | H2: =SUMIFS(D6:D100,C6:C100,"Food & Dining",E6:E100,"Expense")
A3: Net Savings: | B3: =B1-B2 | G3: Transport | H3: =SUMIFS(D6:D100,C6:C100,"Transport",E6:E100,"Expense")
G4: Housing | H4: =SUMIFS(D6:D100,C6:C100,"Housing",E6:E100,"Expense")
A5: Date | B5: Description | C5: Category | D5: Amount | E5: Type | G5: Utilities | H5: =SUMIFS(D6:D100,C6:C100,"Utilities",E6:E100,"Expense")
G6: Entertainment | H6: =SUMIFS(D6:D100,C6:C100,"Entertainment",E6:E100,"Expense")
G7: Shopping | H7: =SUMIFS(D6:D100,C6:C100,"Shopping",E6:E100,"Expense")
G8: Healthcare | H8: =SUMIFS(D6:D100,C6:C100,"Healthcare",E6:E100,"Expense")
G9: Education | H9: =SUMIFS(D6:D100,C6:C100,"Education",E6:E100,"Expense")
G10: Savings | H10: =SUMIFS(D6:D100,C6:C100,"Savings",E6:E100,"Expense")
G11: Other | H11: =SUMIFS(D6:D100,C6:C100,"Other",E6:E100,"Expense")

Sheet November
A1: Total Income: | B1: =SUMIF(E6:E100,"Income",D6:D100) | G1: Category Breakdown
A2: Total Expenses: | B2: =SUMIF(E6:E100,"Expense",D6:D100) | G2: Food & Dining | H2: =SUMIFS(D6:D100,C6:C100,"Food & Dining",E6:E100,"Expense")
A3: Net Savings: | B3: =B1-B2 | G3: Transport | H3: =SUMIFS(D6:D100,C6:C100,"Transport",E6:E100,"Expense")
G4: Housing | H4: =SUMIFS(D6:D100,C6:C100,"Housing",E6:E100,"Expense")
A5: Date | B5: Description | C5: Category | D5: Amount | E5: Type | G5: Utilities | H5: =SUMIFS(D6:D100,C6:C100,"Utilities",E6:E100,"Expense")
G6: Entertainment | H6: =SUMIFS(D6:D100,C6:C100,"Entertainment",E6:E100,"Expense")
G7: Shopping | H7: =SUMIFS(D6:D100,C6:C100,"Shopping",E6:E100,"Expense")
G8: Healthcare | H8: =SUMIFS(D6:D100,C6:C100,"Healthcare",E6:E100,"Expense")
G9: Education | H9: =SUMIFS(D6:D100,C6:C100,"Education",E6:E100,"Expense")
G10: Savings | H10: =SUMIFS(D6:D100,C6:C100,"Savings",E6:E100,"Expense")
G11: Other | H11: =SUMIFS(D6:D100,C6:C100,"Other",E6:E100,"Expense")

Sheet December
A1: Total Income: | B1: =SUMIF(E6:E100,"Income",D6:D100) | G1: Category Breakdown
A2: Total Expenses: | B2: =SUMIF(E6:E100,"Expense",D6:D100) | G2: Food & Dining | H2: =SUMIFS(D6:D100,C6:C100,"Food & Dining",E6:E100,"Expense")
A3: Net Savings: | B3: =B1-B2 | G3: Transport | H3: =SUMIFS(D6:D100,C6:C100,"Transport",E6:E100,"Expense")
G4: Housing | H4: =SUMIFS(D6:D100,C6:C100,"Housing",E6:E100,"Expense")
A5: Date | B5: Description | C5: Category | D5: Amount | E5: Type | G5: Utilities | H5: =SUMIFS(D6:D100,C6:C100,"Utilities",E6:E100,"Expense")
G6: Entertainment | H6: =SUMIFS(D6:D100,C6:C100,"Entertainment",E6:E100,"Expense")
G7: Shopping | H7: =SUMIFS(D6:D100,C6:C100,"Shopping",E6:E100,"Expense")
G8: Healthcare | H8: =SUMIFS(D6:D100,C6:C100,"Healthcare",E6:E100,"Expense")
G9: Education | H9: =SUMIFS(D6:D100,C6:C100,"Education",E6:E100,"Expense")
G10: Savings | H10: =SUMIFS(D6:D100,C6:C100,"Savings",E6:E100,"Expense")
G11: Other | H11: =SUMIFS(D6:D100,C6:C100,"Other",E6:E100,"Expense")

Sheet Budget Goals
A1: Category Budget Planner
A3: Category | B3: Monthly Budget | C3: Actual (Jan) | D3: Difference | E3: Status
A4: Food & Dining | B4: 500 | C4: =January!H2 | D4: =B4-C4 | E4: =IF(D4>=0,"Under Budget","OVER BUDGET")
A5: Transport | B5: 200 | C5: =January!H3 | D5: =B5-C5 | E5: =IF(D5>=0,"Under Budget","OVER BUDGET")
A6: Housing | B6: 1500 | C6: =January!H4 | D6: =B6-C6 | E6: =IF(D6>=0,"Under Budget","OVER BUDGET")
A7: Utilities | B7: 150 | C7: =January!H5 | D7: =B7-C7 | E7: =IF(D7>=0,"Under Budget","OVER BUDGET")
A8: Entertainment | B8: 100 | C8: =January!H6 | D8: =B8-C8 | E8: =IF(D8>=0,"Under Budget","OVER BUDGET")
A9: Shopping | B9: 200 | C9: =January!H7 | D9: =B9-C9 | E9: =IF(D9>=0,"Under Budget","OVER BUDGET")
A10: Healthcare | B10: 100 | C10: =January!H8 | D10: =B10-C10 | E10: =IF(D10>=0,"Under Budget","OVER BUDGET")
A11: Education | B11: 50 | C11: =January!H9 | D11: =B11-C11 | E11: =IF(D11>=0,"Under Budget","OVER BUDGET")
A12: Savings | B12: 500 | C12: =January!H10 | D12: =B12-C12 | E12: =IF(D12>=0,"Under Budget","OVER BUDGET")
A13: Other | B13: 100 | C13: =January!H11 | D13: =B13-C13 | E13: =IF(D13>=0,"Under Budget","OVER BUDGET")
